[{"sidebar-1":["search-2","sf_recent_custom_posts-2","lip_most_loved_widget-2","sf_recent_custom_comments-2"],"sidebar-2":["text-6","archives-2","sf_infocus_widget-2","twitter-widget-3"],"sidebar-8":["text-5"],"footer-column-1":["text-2"],"footer-column-2":["twitter-widget-2"],"footer-column-3":["nav_menu-2"],"footer-column-4":["text-3"]},{"":{"ction":null,"_multiwidget":null,"wpnonce":null,"wp_http_referer":null},"search":{"2":{"title":""},"_multiwidget":1},"sf_recent_custom_posts":{"2":{"title":"Latest News","number":"3","category":"All"},"_multiwidget":1},"lip_most_loved_widget":{"2":{"title":"Most Popular","number":"3"},"_multiwidget":1},"sf_recent_custom_comments":{"2":{"title":"Recent Comments","number":"3"},"_multiwidget":1},"text":{"6":{"title":"","text":"<div style=\"background: #f7f7f7; padding: 40px;\"><h4 style=\"text-align: center; text-transform: uppercase;\">Cardinal Newsletter<\/h4><p>[hr]<\/p><p>[contact-form-7 id=\"11403\" title=\"Subscribe\"]<\/p><p style=\"text-align: center;\">Sign up for our weekly bulletin<\/p><\/div>","filter":false},"5":{"title":"","text":"<a href=\"http:\/\/cardinal.swiftideas.com\/magazine-demo\" style=\"display:inline-block; margin:0 5px;\">HOME<\/a> | <a href=\"http:\/\/cardinal.swiftideas.com\/magazine-demo\/advertise\" style=\"display:inline-block; margin:0 5px;\">ADVERTISE WITH US<\/a> | <a href=\"http:\/\/cardinal.swiftideas.com\/magazine-demo\/contact-us\" style=\"display:inline-block; margin:0 5px;\">CONTACT<\/a>","filter":false},"2":{"title":"About Cardinal","text":"Lorem ipsum dolor sit amet, consectetur adipiscing elit. Nam viverra euismod odio, gravida pellentesque urna varius vitae. Sed dui lorem, adipiscing in adipiscing et, interdum nec metus. Mauris ultricies, justo eu convallis placerat, felis enim ornare nisi, vitae mattis nulla ante id dui.","filter":false},"3":{"title":"Follow Us","text":"[social style='light' size=\"large\"]\r\n<hr>\r\n<p style=\"margin-bottom: 10px;\">Sign up for our newsletter:<\/p>\r\n<div id=\"mc_embed_signup\">\r\n<form action=\"http:\/\/edcousins.us2.list-manage1.com\/subscribe\/post?u=a3950048c69f7be72a27013a9&amp;id=68a002176a\" method=\"post\" id=\"mc-embedded-subscribe-form\" name=\"mc-embedded-subscribe-form\" class=\"validate\" target=\"_blank\" novalidate>\r\n    <input type=\"email\" value=\"\" name=\"EMAIL\" class=\"email\" id=\"mce-EMAIL\" placeholder=\"Enter your email address here\" style=\"margin-bottom: 0;\" required>\r\n    <div class=\"clear\"><input type=\"submit\" value=\"Subscribe\" name=\"subscribe\" id=\"mc-embedded-subscribe\" class=\"button\" style=\"visibility:hidden;\"><\/div>\r\n<\/form>\r\n<\/div>","filter":false},"_multiwidget":1},"archives":{"2":{"title":"","count":0,"dropdown":0},"_multiwidget":1},"sf_infocus_widget":{"2":{"title":"In Focus","post_id":"11258"},"_multiwidget":1},"twitter-widget":{"3":{"title":"Latest Tweets","username":"swiftideas","posts":"3","date":null,"datedisplay":null,"clickable":null,"hideerrors":null,"encodespecial":null},"2":{"title":"Latest Tweets","username":"swiftideas","posts":"2","date":null,"datedisplay":null,"clickable":null,"hideerrors":null,"encodespecial":null},"_multiwidget":1},"nav_menu":{"2":{"title":"Categories","nav_menu":15},"_multiwidget":1}}]